{
  "project_info": {
    "project_number": "943464328976",
    "firebase_url": "https://fitfifteen-160817.firebaseio.com",
    "project_id": "fitfifteen-160817",
    "storage_bucket": "fitfifteen-160817.appspot.com"
  },
  "client": [
    {
      "client_info": {
        "mobilesdk_app_id": "1:943464328976:android:850aeae70f61a77d",
        "android_client_info": {
          "package_name": "come.fitfifteen.android"
        }
      },
      "oauth_client": [
        {
          "client_id": "943464328976-mvos1c0cph4se1aqp49pppfj22s6k3pl.apps.googleusercontent.com",
          "client_type": 3
        }
      ],
      "api_key": [
        {
          "current_key": "AIzaSyCNKq2u0bprJrN_blqVHja4DgQVnCQm_-4"
        }
      ],
      "services": {
        "analytics_service": {
          "status": 1
        },
        "appinvite_service": {
          "status": 1,
          "other_platform_oauth_client": []
        },
        "ads_service": {
          "status": 2
        }
      }
    }
  ],
  "configuration_version": "1"
}